LICENSE
README.md
setup.py
GeneticAlgorithmFeaturesSelection/GA.py
GeneticAlgorithmFeaturesSelection/__init__.py
GeneticAlgorithmFeaturesSelection.egg-info/PKG-INFO
GeneticAlgorithmFeaturesSelection.egg-info/SOURCES.txt
GeneticAlgorithmFeaturesSelection.egg-info/dependency_links.txt
GeneticAlgorithmFeaturesSelection.egg-info/requires.txt
GeneticAlgorithmFeaturesSelection.egg-info/top_level.txt
tests/__init__.py
tests/test.py